repo_to_singlefile/__init__.py
repo_to_singlefile/cli.py
repo_to_singlefile/converter.py
repo_to_singlefile/github.py
repo_to_singlefile/local.py
repo_to_singlefile-0.1.0.dist-info/METADATA
repo_to_singlefile-0.1.0.dist-info/WHEEL
repo_to_singlefile-0.1.0.dist-info/entry_points.txt
repo_to_singlefile-0.1.0.dist-info/RECORD
