Metadata-Version: 2.1
Name: repo-to-singlefile
Version: 0.1.0
Summary: A tool to convert code repositories into text format for LLM context
Home-page: https://github.com/Oni-giri/repo-to-singlefile
License: MIT
Keywords: repository,text,llm,context,converter
Author: Yakitori
Author-email: mers_etanche.0n@icloud.com
Requires-Python: >=3.8,<4.0
Classifier: Development Status :: 4 - Beta
Classifier: Environment :: Console
Classifier: Intended Audience :: Developers
Classifier: License :: OSI Approved :: MIT License
Classifier: Programming Language :: Python :: 3
Classifier: Programming Language :: Python :: 3.8
Classifier: Programming Language :: Python :: 3.9
Classifier: Programming Language :: Python :: 3.10
Classifier: Programming Language :: Python :: 3.11
Classifier: Programming Language :: Python :: 3.12
Classifier: Programming Language :: Python :: 3.13
Classifier: Topic :: Software Development :: Libraries :: Python Modules
Classifier: Topic :: Text Processing :: General
Requires-Dist: gitpython (>=3.1.0,<4.0.0)
Requires-Dist: requests (>=2.31.0,<3.0.0)
Requires-Dist: tiktoken (>=0.5.1,<0.6.0)
Requires-Dist: typing-extensions (>=4.5.0,<5.0.0)
Project-URL: Repository, https://github.com/Oni-giri/repo-to-singlefile
